<?xml version="1.0" encoding="UTF-8"?><record_update>
    <sys_choice action="DELETE" field="state" table="x_58872_needit_needit" version="3">
        <sys_choice action="INSERT_OR_UPDATE">
            <dependent_value/>
            <element>state</element>
            <hint/>
            <inactive>false</inactive>
            <label>Requested</label>
            <language>en</language>
            <name>x_58872_needit_needit</name>
            <sequence>0</sequence>
            <sys_created_by>admin</sys_created_by>
            <sys_created_on>2017-01-26 20:14:39</sys_created_on>
            <sys_domain>global</sys_domain>
            <sys_domain_path>/</sys_domain_path>
            <sys_id>e0b229350fa03200cd674f8ce1050ea9</sys_id>
            <sys_mod_count>0</sys_mod_count>
            <sys_updated_by>admin</sys_updated_by>
            <sys_updated_on>2017-01-26 20:14:39</sys_updated_on>
            <value>13</value>
        </sys_choice>
        <sys_choice action="INSERT_OR_UPDATE">
            <dependent_value/>
            <element>state</element>
            <hint/>
            <inactive>false</inactive>
            <label>Awaiting Approval</label>
            <language>en</language>
            <name>x_58872_needit_needit</name>
            <sequence>1</sequence>
            <sys_created_by>admin</sys_created_by>
            <sys_created_on>2017-01-26 20:14:39</sys_created_on>
            <sys_domain>global</sys_domain>
            <sys_domain_path>/</sys_domain_path>
            <sys_id>ecb229350fa03200cd674f8ce1050eaa</sys_id>
            <sys_mod_count>0</sys_mod_count>
            <sys_updated_by>admin</sys_updated_by>
            <sys_updated_on>2017-01-26 20:14:39</sys_updated_on>
            <value>14</value>
        </sys_choice>
        <sys_choice action="INSERT_OR_UPDATE">
            <dependent_value/>
            <element>state</element>
            <hint/>
            <inactive>false</inactive>
            <label>Approved</label>
            <language>en</language>
            <name>x_58872_needit_needit</name>
            <sequence>2</sequence>
            <sys_created_by>admin</sys_created_by>
            <sys_created_on>2017-01-26 20:14:39</sys_created_on>
            <sys_domain>global</sys_domain>
            <sys_domain_path>/</sys_domain_path>
            <sys_id>28b229350fa03200cd674f8ce1050eac</sys_id>
            <sys_mod_count>0</sys_mod_count>
            <sys_updated_by>admin</sys_updated_by>
            <sys_updated_on>2017-01-26 20:14:39</sys_updated_on>
            <value>15</value>
        </sys_choice>
        <sys_choice action="INSERT_OR_UPDATE">
            <dependent_value/>
            <element>state</element>
            <hint/>
            <inactive>false</inactive>
            <label>Awaiting Feedback</label>
            <language>en</language>
            <name>x_58872_needit_needit</name>
            <sequence>3</sequence>
            <sys_created_by>admin</sys_created_by>
            <sys_created_on>2017-01-26 20:14:39</sys_created_on>
            <sys_domain>global</sys_domain>
            <sys_domain_path>/</sys_domain_path>
            <sys_id>60b229350fa03200cd674f8ce1050eae</sys_id>
            <sys_mod_count>0</sys_mod_count>
            <sys_updated_by>admin</sys_updated_by>
            <sys_updated_on>2017-01-26 20:14:39</sys_updated_on>
            <value>16</value>
        </sys_choice>
        <sys_choice action="INSERT_OR_UPDATE">
            <dependent_value/>
            <element>state</element>
            <hint/>
            <inactive>false</inactive>
            <label>Closed Complete</label>
            <language>en</language>
            <name>x_58872_needit_needit</name>
            <sequence>4</sequence>
            <sys_created_by>admin</sys_created_by>
            <sys_created_on>2017-01-26 20:14:39</sys_created_on>
            <sys_domain>global</sys_domain>
            <sys_domain_path>/</sys_domain_path>
            <sys_id>a8b229350fa03200cd674f8ce1050eaf</sys_id>
            <sys_mod_count>0</sys_mod_count>
            <sys_updated_by>admin</sys_updated_by>
            <sys_updated_on>2017-01-26 20:14:39</sys_updated_on>
            <value>3</value>
        </sys_choice>
        <sys_choice action="INSERT_OR_UPDATE">
            <dependent_value/>
            <element>state</element>
            <hint/>
            <inactive>false</inactive>
            <label>Withdrawn</label>
            <language>en</language>
            <name>x_58872_needit_needit</name>
            <sequence>5</sequence>
            <sys_created_by>admin</sys_created_by>
            <sys_created_on>2017-01-26 20:14:39</sys_created_on>
            <sys_domain>global</sys_domain>
            <sys_domain_path>/</sys_domain_path>
            <sys_id>a0b229350fa03200cd674f8ce1050eb1</sys_id>
            <sys_mod_count>0</sys_mod_count>
            <sys_updated_by>admin</sys_updated_by>
            <sys_updated_on>2017-01-26 20:14:39</sys_updated_on>
            <value>8</value>
        </sys_choice>
        <sys_choice_set action="INSERT_OR_UPDATE">
            <element>state</element>
            <name>x_58872_needit_needit</name>
            <sys_class_name>sys_choice_set</sys_class_name>
            <sys_created_by>admin</sys_created_by>
            <sys_created_on>2017-01-26 20:14:39</sys_created_on>
            <sys_id>0c4ec4d54f321300874e8020a310c7ec</sys_id>
            <sys_mod_count>1</sys_mod_count>
            <sys_name>state</sys_name>
            <sys_package display_value="NeedIt" source="x_58872_needit">6ead8e780f603200cd674f8ce1050ed1</sys_package>
            <sys_policy/>
            <sys_scope display_value="NeedIt">6ead8e780f603200cd674f8ce1050ed1</sys_scope>
            <sys_update_name>sys_choice_x_58872_needit_needit_state</sys_update_name>
            <sys_updated_by>admin</sys_updated_by>
            <sys_updated_on>2017-01-26 20:14:39</sys_updated_on>
        </sys_choice_set>
    </sys_choice>
<sys_update_version action="INSERT_OR_UPDATE">
        <action>DELETE</action>
        <application display_value="NeedIt">6ead8e780f603200cd674f8ce1050ed1</application>
        <file_path/>
        <instance_id>3506a242db531b800e785d00cf9619c7</instance_id>
        <instance_name>dev65181</instance_name>
        <name>sys_choice_x_58872_needit_needit_state</name>
        <payload><![CDATA[<?xml version="1.0" encoding="UTF-8"?><record_update>
    <sys_choice action="INSERT_OR_UPDATE" field="state" table="x_58872_needit_needit" version="3">
        <sys_choice action="INSERT_OR_UPDATE">
            <dependent_value/>
            <element>state</element>
            <hint/>
            <inactive>false</inactive>
            <label>Requested</label>
            <language>en</language>
            <name>x_58872_needit_needit</name>
            <sequence>0</sequence>
            <sys_created_by>admin</sys_created_by>
            <sys_created_on>2017-01-26 20:14:39</sys_created_on>
            <sys_domain>global</sys_domain>
            <sys_domain_path>/</sys_domain_path>
            <sys_id>e0b229350fa03200cd674f8ce1050ea9</sys_id>
            <sys_mod_count>0</sys_mod_count>
            <sys_updated_by>admin</sys_updated_by>
            <sys_updated_on>2017-01-26 20:14:39</sys_updated_on>
            <value>13</value>
        </sys_choice>
        <sys_choice action="INSERT_OR_UPDATE">
            <dependent_value/>
            <element>state</element>
            <hint/>
            <inactive>false</inactive>
            <label>Awaiting Approval</label>
            <language>en</language>
            <name>x_58872_needit_needit</name>
            <sequence>1</sequence>
            <sys_created_by>admin</sys_created_by>
            <sys_created_on>2017-01-26 20:14:39</sys_created_on>
            <sys_domain>global</sys_domain>
            <sys_domain_path>/</sys_domain_path>
            <sys_id>ecb229350fa03200cd674f8ce1050eaa</sys_id>
            <sys_mod_count>0</sys_mod_count>
            <sys_updated_by>admin</sys_updated_by>
            <sys_updated_on>2017-01-26 20:14:39</sys_updated_on>
            <value>14</value>
        </sys_choice>
        <sys_choice action="INSERT_OR_UPDATE">
            <dependent_value/>
            <element>state</element>
            <hint/>
            <inactive>false</inactive>
            <label>Approved</label>
            <language>en</language>
            <name>x_58872_needit_needit</name>
            <sequence>2</sequence>
            <sys_created_by>admin</sys_created_by>
            <sys_created_on>2017-01-26 20:14:39</sys_created_on>
            <sys_domain>global</sys_domain>
            <sys_domain_path>/</sys_domain_path>
            <sys_id>28b229350fa03200cd674f8ce1050eac</sys_id>
            <sys_mod_count>0</sys_mod_count>
            <sys_updated_by>admin</sys_updated_by>
            <sys_updated_on>2017-01-26 20:14:39</sys_updated_on>
            <value>15</value>
        </sys_choice>
        <sys_choice action="INSERT_OR_UPDATE">
            <dependent_value/>
            <element>state</element>
            <hint/>
            <inactive>false</inactive>
            <label>Awaiting Feedback</label>
            <language>en</language>
            <name>x_58872_needit_needit</name>
            <sequence>3</sequence>
            <sys_created_by>admin</sys_created_by>
            <sys_created_on>2017-01-26 20:14:39</sys_created_on>
            <sys_domain>global</sys_domain>
            <sys_domain_path>/</sys_domain_path>
            <sys_id>60b229350fa03200cd674f8ce1050eae</sys_id>
            <sys_mod_count>0</sys_mod_count>
            <sys_updated_by>admin</sys_updated_by>
            <sys_updated_on>2017-01-26 20:14:39</sys_updated_on>
            <value>16</value>
        </sys_choice>
        <sys_choice action="INSERT_OR_UPDATE">
            <dependent_value/>
            <element>state</element>
            <hint/>
            <inactive>false</inactive>
            <label>Closed Complete</label>
            <language>en</language>
            <name>x_58872_needit_needit</name>
            <sequence>4</sequence>
            <sys_created_by>admin</sys_created_by>
            <sys_created_on>2017-01-26 20:14:39</sys_created_on>
            <sys_domain>global</sys_domain>
            <sys_domain_path>/</sys_domain_path>
            <sys_id>a8b229350fa03200cd674f8ce1050eaf</sys_id>
            <sys_mod_count>0</sys_mod_count>
            <sys_updated_by>admin</sys_updated_by>
            <sys_updated_on>2017-01-26 20:14:39</sys_updated_on>
            <value>3</value>
        </sys_choice>
        <sys_choice action="INSERT_OR_UPDATE">
            <dependent_value/>
            <element>state</element>
            <hint/>
            <inactive>false</inactive>
            <label>Withdrawn</label>
            <language>en</language>
            <name>x_58872_needit_needit</name>
            <sequence>5</sequence>
            <sys_created_by>admin</sys_created_by>
            <sys_created_on>2017-01-26 20:14:39</sys_created_on>
            <sys_domain>global</sys_domain>
            <sys_domain_path>/</sys_domain_path>
            <sys_id>a0b229350fa03200cd674f8ce1050eb1</sys_id>
            <sys_mod_count>0</sys_mod_count>
            <sys_updated_by>admin</sys_updated_by>
            <sys_updated_on>2017-01-26 20:14:39</sys_updated_on>
            <value>8</value>
        </sys_choice>
        <sys_choice_set action="INSERT_OR_UPDATE">
            <element>state</element>
            <name>x_58872_needit_needit</name>
            <sys_class_name>sys_choice_set</sys_class_name>
            <sys_created_by>admin</sys_created_by>
            <sys_created_on>2017-01-26 20:14:39</sys_created_on>
            <sys_id>0c4ec4d54f321300874e8020a310c7ec</sys_id>
            <sys_mod_count>1</sys_mod_count>
            <sys_name>state</sys_name>
            <sys_package display_value="NeedIt" source="x_58872_needit">6ead8e780f603200cd674f8ce1050ed1</sys_package>
            <sys_policy/>
            <sys_scope display_value="NeedIt">6ead8e780f603200cd674f8ce1050ed1</sys_scope>
            <sys_update_name>sys_choice_x_58872_needit_needit_state</sys_update_name>
            <sys_updated_by>admin</sys_updated_by>
            <sys_updated_on>2017-01-26 20:14:39</sys_updated_on>
        </sys_choice_set>
    </sys_choice>
</record_update>]]></payload>
        <payload_hash>-1231798200</payload_hash>
        <record_name>NeedIt.State</record_name>
        <reverted_from/>
        <source>8c2b8ad7db53501054b7112039961988</source>
        <source_table>sys_upgrade_history</source_table>
        <state>previous</state>
        <sys_created_by>admin</sys_created_by>
        <sys_created_on>2020-09-22 09:01:58</sys_created_on>
        <sys_id>722b8ed7db53501054b7112039961946</sys_id>
        <sys_mod_count>0</sys_mod_count>
        <sys_recorded_at>174b50c53960000001</sys_recorded_at>
        <sys_updated_by>admin</sys_updated_by>
        <sys_updated_on>2020-09-22 09:01:58</sys_updated_on>
        <type>Choice list</type>
        <update_guid>fe2b8ed70f5350105a40280841eb0a45</update_guid>
        <update_guid_history>fe2b8ed70f5350105a40280841eb0a45:0,742bcad72c535010ce2ff20ccaab6308:1528579032,bc2bcad7b953501056ca704f5afb6f04:1886447883,a82bcad7c55350107451d7316fd21801:-1196625253,a42b8ad720535010c5c33571457f86fe:-1669741480,602b8ad7655350103070ff2cd2d5befb:775889921,2c2b8ad7b9535010ea2c9225c3bf26f7:-1246223066,78931e4af713d01047e17b30b5ae43f2:0,6783da4a0313d0101a2843cb29f63c29:1528579032,af83da4afc13d0100a737ad0bad18025:1886447883,ab83da4afa13d010525613de015e4322:-1196625253,a783da4ac913d01070039e0e408f111f:-1669741480,a383da4a1e13d0103133af75edbe8e1c:775889921,af83da4ad713d010be52290e31494718:-1246223066,dd3c418ada5f901011abcded282afb72:0,043ccd4a2f5f9010cb7b777c8b0e35e8:1528579032,4c3ccd4aec5f9010a0cc6d36648849e4:1886447883,483ccd4ac65f90104bc64931a78fdfe1:-1196625253,443ccd4ad45f9010fd853fd962ff01de:-1669741480,403ccd4a0f5f90102287bc9ed83355db:775889921,4c3ccd4a815f90108c704d59648096d7:-1246223066,8ff505b1c5d3901081f2d4654fbeb409:0,02f581b1c0d3901099e79cc20c76999c:1528579032,4af581b11ad39010e6859ffdd168d698:1886447883,46f581b108d390105d1f14ca4d270095:-1196625253,42f581b17bd3901073e7d6ad8646cb92:-1669741480,4ef581b107d390105783ad94fdd2018e:775889921,4af581b158d390102683bf10f4e3fe8b:-1246223066,ad07f8f5bc939010fa6d47c8ec6391b9:0,5ff678f526939010193ae32ce6ee8cf5:1528579032,97f678f5d2939010a7e3ebbc30d233f2:1886447883,83f678f51d939010abaf043c00282cef:-1196625253,8ff678f52c939010f6e889e8476545eb:-1669741480,c3f678f564939010f5845421d9efd1dc:775889921,cff678f52393901051c7297a6020bed8:-1246223066,17a0583d411390107806a928b10aa044:0,06a0d43dfb13901078659bd19b8f9253:1528579032,4ea0d43d79139010e5d9f42f0e77a54f:1886447883,79a0d43d0f139010436a8343156dc24c:-1196625253,75a0d43d6a1390109fc0362396bc0649:-1669741480,71a0d43d8113901019871d14fb1f9346:775889921,7da0d43dd9139010350891fd0f5ddf42:-1246223066,bef7f7e96cdf50103fa4651f7a6aef14:0,2df737e9dedf5010a0695e78380df0ec:1528579032,65f737e945df50101c09c09655b633e9:1886447883,61f737e92bdf50103a376f706c4550e6:-1196625253,6df737e98edf5010ec97e3ed103053e2:-1669741480,61f737e9d6df5010653f99584c8b5fd3:775889921,2df737e9e3df50104fd6666cb872aacf:-1246223066,f50253a1839f5010c40f5052f9e8785f:0,a802df61859f5010384abcc9e1f7e926:1528579032,e002df61e29f50106c485d87daa93e23:1886447883,ec02df61a09f5010bad8b823cf7f911f:-1196625253,e802df619f9f50105be6098eada93a1c:-1669741480,a402df61e09f50103f1b12da87a80d19:775889921,6002df61ad9f50107c8ffed523b53d16:-1246223066,e339cbd524d35010f205408da679ae2a:0,32398bd5bad3501028abbc452b03d13b:1528579032,b2398bd583d350103ff1cd8169072a2b:1886447883,be398bd577d350102370528292ffe127:-1196625253,ba398bd5cad3501051ae12abea2bf424:-1669741480,76398bd563d35010b08bd0da93233221:775889921,b2398bd56ad35010f53afd4cf83b4f05:-1246223066,0770f29557935010d0d3cca1f202c55c:0,9670b2958d9350104fa90a7d4357d341:1528579032,de70b29591935010a25e0e2c8d4d003d:1886447883,da70b295f59350103ebe89304993cb3a:-1196625253,d670b295cb93501009e04381cf6eca37:-1669741480,d270b2953f935010297c835196dc5934:775889921,de70b295da9350103c19ab6c3d34e330:-1246223066,823e5659795350106036e0e85bc9667a:0,503e92591f53501035987d37bbd613f1:1528579032,183e92598f535010b5634ae99f07bfed:1886447883,143e9259835350100cd2d1cc3d0d28ea:-1196625253,103e925932535010243418f47bc789e7:-1669741480,d83e92599b53501039b62288ae7fc8e3:775889921,943e925908535010cd1e6e246b569be0:-1246223066,67c6a785ba9b10102edb3e756de6847b:-1617139336,94f56f45dc9b10109cc6a10cbe836413:-2037482732</update_guid_history>
    </sys_update_version>
    <sys_metadata_delete action="INSERT_OR_UPDATE">
        <sys_audit_delete/>
        <sys_class_name>sys_metadata_delete</sys_class_name>
        <sys_created_by>admin</sys_created_by>
        <sys_created_on>2020-09-23 04:35:17</sys_created_on>
        <sys_db_object display_value="" name="sys_choice_set">sys_choice_set</sys_db_object>
        <sys_id>fa2b8ed7db53501054b711203996193b</sys_id>
        <sys_metadata>fa2b8ed7db53501054b711203996193b</sys_metadata>
        <sys_mod_count>0</sys_mod_count>
        <sys_name>state</sys_name>
        <sys_package display_value="NeedIt" source="x_58872_needit">6ead8e780f603200cd674f8ce1050ed1</sys_package>
        <sys_parent/>
        <sys_policy/>
        <sys_scope display_value="NeedIt">6ead8e780f603200cd674f8ce1050ed1</sys_scope>
        <sys_scope_delete display_value="">94872a8897db403e8ee69a431de2fca4</sys_scope_delete>
        <sys_update_name>sys_choice_x_58872_needit_needit_state</sys_update_name>
        <sys_update_version display_value="sys_choice_x_58872_needit_needit_state">722b8ed7db53501054b7112039961946</sys_update_version>
        <sys_updated_by>admin</sys_updated_by>
        <sys_updated_on>2020-09-23 04:35:17</sys_updated_on>
    </sys_metadata_delete>
</record_update>
